LICENSE
gordo_dataset/__init__.py
gordo_dataset/assets_config.py
gordo_dataset/base.py
gordo_dataset/data_provider/__init__.py
gordo_dataset/data_provider/base.py
gordo_dataset/data_provider/constants.py
gordo_dataset/data_provider/file_type.py
gordo_dataset/data_provider/measurement_mapper.py
gordo_dataset/data_provider/ncs_contants.py
gordo_dataset/data_provider/ncs_file_type.py
gordo_dataset/data_provider/ncs_lookup.py
gordo_dataset/data_provider/ncs_reader.py
gordo_dataset/data_provider/partition.py
gordo_dataset/data_provider/providers.py
gordo_dataset/data_provider/ren_lookup.py
gordo_dataset/data_provider/ren_provider.py
gordo_dataset/data_provider/secrets_loaders.py
gordo_dataset/data_provider/storages.py
gordo_dataset/data_provider/utils.py
gordo_dataset/dataset.py
gordo_dataset/dataset_metadata.py
gordo_dataset/datasets.py
gordo_dataset/dependencies.py
gordo_dataset/dimensions.py
gordo_dataset/exceptions.py
gordo_dataset/file_system/__init__.py
gordo_dataset/file_system/adl1.py
gordo_dataset/file_system/adl2.py
gordo_dataset/file_system/azure.py
gordo_dataset/file_system/base.py
gordo_dataset/filter_periods.py
gordo_dataset/filter_rows.py
gordo_dataset/ren_dataset.py
gordo_dataset/resource_assets_config.py
gordo_dataset/resources/__init__.py
gordo_dataset/resources/assets_config.yaml
gordo_dataset/sensor_tag.py
gordo_dataset/utils.py
gordo_dataset/validators.py
gordo_dataset-3.1.2.dist-info/LICENSE
gordo_dataset-3.1.2.dist-info/WHEEL
gordo_dataset-3.1.2.dist-info/METADATA
gordo_dataset-3.1.2.dist-info/RECORD
